flask_geolocation/__about__.py
flask_geolocation/__init__.py
flask_geolocation/geo.py
flask_geolocation/geo_manager.py
flask_geolocation/ip_database.py
flask_geolocation/timezone.py
flask_geolocation/utils.py
Flask_Geolocation-0.1.1.dist-info/LICENSE
Flask_Geolocation-0.1.1.dist-info/METADATA
Flask_Geolocation-0.1.1.dist-info/WHEEL
Flask_Geolocation-0.1.1.dist-info/top_level.txt
Flask_Geolocation-0.1.1.dist-info/RECORD
