Metadata-Version: 2.1
Name: Flask-Geolocation
Version: 0.1.1
Summary: getting user geolocation for Flask
Home-page: https://github.com/wankai/flask-geo
Author: Wankai Zhang
Author-email: wankaizhang@gmail.com
Maintainer: Wankai Zhang
License: MIT
Project-URL: Source Code, https://github.com/wankai/flask-geo
Classifier: Development Status :: 4 - Beta
Classifier: Environment :: Web Environment
Classifier: Framework :: Flask
Classifier: Intended Audience :: Developers
Classifier: License :: OSI Approved :: MIT License
Classifier: Operating System :: OS Independent
Classifier: Programming Language :: Python
Classifier: Topic :: Internet :: WWW/HTTP :: Dynamic Content
Classifier: Topic :: Software Development :: Libraries :: Python Modules
Requires-Python: >=3.7
License-File: LICENSE
Requires-Dist: Flask (>=1.0.4)
Requires-Dist: Werkzeug (>=1.0.1)
